{
  "fullName": "Abutilon x hybridum",
  "name": "abutilon-x-hybridum",
  "commonNames": [
    "Chinese Bellflower",
    "Chinese Lantern",
    "Flowering Maple",
    "Parlor Maple"
  ],
  "references": [
    {
      "url": "https://plants.ces.ncsu.edu/plants/abutilon-x-hybridum/",
      "referenced": "general plant data"
    }
  ],
  "genus": "Abutilon",
  "family": "Malvaceae",
  "life-cycle": [
    "Woody"
  ],
  "recommended-propagation-strategy": [
    "Seed",
    "Stem Cutting"
  ],
  "country-or-region-of-origin": [
    "Unsure- perhaps S. America"
  ],
  "edibility": [
    "Flowers are edible raw or cooked with a sweet flavor"
  ],
  "dimensions": [
    "Height: 8 ft. 0 in. - 10 ft. 0 in.",
    "Width: 2 ft. 0 in. - 5 ft. 0 in."
  ],
  "plant-type": [
    "Shrub"
  ],
  "woody-plant-leaf-characteristics": [
    "Broadleaf Evergreen",
    "Broadleaf Evergreen"
  ],
  "habit/form": [
    "Arching",
    "Erect"
  ],
  "growth-rate": [
    "Rapid"
  ],
  "maintenance": [
    "Low",
    "Medium"
  ],
  "texture": [
    "Medium"
  ],
  "light": [
    "Full sun (6 or more hours of direct sunlight a day)",
    "Partial Shade (Direct sunlight only part of the day, 2-6 hours)"
  ],
  "soil-texture": [
    "Clay",
    "High Organic Matter",
    "Loam (Silt)"
  ],
  "soil-drainage": [
    "Good Drainage",
    "Moist",
    "Occasionally Wet"
  ],
  "available-space-to-plant": [
    "12 inches-3 feet"
  ],
  "usda-plant-hardiness-zone": [
    "9a",
    "9b",
    "10a",
    "10b"
  ],
  "fruit-type": [
    "Schizocarp"
  ],
  "flower-color": [
    "Gold/Yellow",
    "Orange",
    "Pink",
    "Red/Burgundy",
    "Variegated",
    "White"
  ],
  "flower-inflorescence": [
    "Solitary"
  ],
  "flower-value-to-gardener": [
    "Showy"
  ],
  "flower-bloom-time": [
    "Fall",
    "Spring",
    "Summer"
  ],
  "flower-shape": [
    "Bell",
    "Cup"
  ],
  "flower-petals": [
    "4-5 petals/rays"
  ],
  "flower-size": [
    "1-3 inches"
  ],
  "flower-description": [
    "Flowers are single in leaf axils, drooping, have 5 petals that are 2 inches long, and have stamens fused into a tubular column. Flowers are white, red, yellow, pink, or orange."
  ],
  "leaf-color": [
    "Gold/Yellow",
    "Green",
    "Variegated"
  ],
  "leaf-value-to-gardener": [
    "Showy"
  ],
  "leaf-type": [
    "Simple"
  ],
  "leaf-arrangement": [
    "Alternate"
  ],
  "leaf-shape": [
    "Cordate",
    "Palmatifid"
  ],
  "leaf-margin": [
    "Crenate",
    "Lobed",
    "Serrate"
  ],
  "hairs-present": [
    "No"
  ],
  "leaf-description": [
    "This shrub has leaves that are alternate, simple, maple-like lobed, often variegated, with toothed margins (serrate to crenate) and a pointed tip."
  ],
  "stem-color": [
    "Green"
  ],
  "stem-is-aromatic": "N",
  "stem-description": [
    "Stems tend to be weak. Pinch back to promote stronger, compact plant."
  ],
  "landscape-location": [
    "Container",
    "Houseplants",
    "Patio"
  ],
  "design-feature": [
    "Accent",
    "Border",
    "Small groups",
    "Specimen"
  ],
  "resistance-to-challenges": [
    "Wet Soil"
  ],
  "problems": [
    "Contact Dermatitis",
    "Poisonous to Humans"
  ]
}