{
  "fullName": "Agastache 'Blue Boa'",
  "name": "agastache-blue-boa",
  "commonNames": [
    "'Blue Boa' Giant Hyssop",
    "Blue Boa Hummingbird Mint",
    "'Giant Hyssop'"
  ],
  "references": [
    {
      "url": "https://plants.ces.ncsu.edu/plants/agastache-blue-boa/",
      "referenced": "general plant data"
    }
  ],
  "genus": "Agastache",
  "family": "Lamiaceae",
  "life-cycle": [
    "Biennial"
  ],
  "country-or-region-of-origin": [
    "SW USA"
  ],
  "wildlife-value": [
    "Attracts a variety of pollinators"
  ],
  "particularly-resistant-to-insects/diseases/other-problems": [
    "Deer and rabbit resistant"
  ],
  "dimensions": [
    "Height: 2 ft. 0 in. - 2 ft. 6 in.",
    "Width: 1 ft. 6 in. - 2 ft. 0 in."
  ],
  "plant-type": [
    "Herbaceous Perennial",
    "Perennial"
  ],
  "woody-plant-leaf-characteristics": [
    "Deciduous",
    "Deciduous"
  ],
  "habit/form": [
    "Clumping",
    "Erect"
  ],
  "growth-rate": [
    "Medium"
  ],
  "maintenance": [
    "Low"
  ],
  "texture": [
    "Medium"
  ],
  "light": [
    "Full sun (6 or more hours of direct sunlight a day)"
  ],
  "soil-texture": [
    "Loam (Silt)",
    "Sand"
  ],
  "soil-ph": [
    "Alkaline (>8.0)",
    "Neutral (6.0-8.0)"
  ],
  "soil-drainage": [
    "Good Drainage",
    "Occasionally Dry"
  ],
  "usda-plant-hardiness-zone": [
    "5a",
    "5b",
    "6a",
    "6b",
    "7a",
    "7b",
    "8a",
    "8b"
  ],
  "display/harvest-time": [
    "Fall",
    "Summer"
  ],
  "fruit-type": [
    "Capsule"
  ],
  "flower-color": [
    "Blue",
    "Purple/Lavender"
  ],
  "flower-inflorescence": [
    "Spike"
  ],
  "flower-value-to-gardener": [
    "Fragrant"
  ],
  "flower-bloom-time": [
    "Fall",
    "Summer"
  ],
  "flower-shape": [
    "Tubular"
  ],
  "flower-size": [
    "< 1 inch"
  ],
  "flower-description": [
    "6-inch terminal spikes of dense lavender-blue flowers"
  ],
  "leaf-color": [
    "Green"
  ],
  "leaf-value-to-gardener": [
    "Fragrant"
  ],
  "leaf-type": [
    "Simple"
  ],
  "leaf-arrangement": [
    "Opposite"
  ],
  "leaf-margin": [
    "Dentate",
    "Serrate"
  ],
  "hairs-present": [
    "No"
  ],
  "leaf-length": [
    "1-3 inches"
  ],
  "leaf-width": [
    "1-3 inches"
  ],
  "leaf-description": [
    "Fragrant medium green leaves with serrated margins. Up to 2.5 inches long and 1.5 inches wide"
  ],
  "stem-color": [
    "Green"
  ],
  "stem-is-aromatic": "N",
  "stem-cross-section": [
    "Square"
  ],
  "stem-description": [
    "Square green stems"
  ],
  "landscape-theme": [
    "Drought Tolerant Garden",
    "Pollinator Garden"
  ],
  "design-feature": [
    "Border"
  ],
  "attracts": [
    "Pollinators"
  ],
  "resistance-to-challenges": [
    "Deer",
    "Drought",
    "Rabbits"
  ]
}