{
  "fullName": "Malus domestica 'GoldRush'",
  "name": "malus-domestica-goldrush",
  "commonNames": [
    "Gold Rush Apple",
    "Goldrush Apple"
  ],
  "references": [
    {
      "url": "https://plants.ces.ncsu.edu/plants/malus-domestica-goldrush/",
      "referenced": "general plant data"
    }
  ],
  "genus": "Malus",
  "species": "domestica",
  "family": "Rosaceae",
  "life-cycle": [
    "Woody"
  ],
  "wildlife-value": [
    "Mason bees pollinate the flowers."
  ],
  "edibility": [
    "Fruits are highly edible used as a winter dessert apple fresh, in pies or crisps, or juiced into cider.  It has good storage ability."
  ],
  "plant-type": [
    "Tree"
  ],
  "woody-plant-leaf-characteristics": [
    "Deciduous",
    "Deciduous"
  ],
  "habit/form": [
    "Erect"
  ],
  "growth-rate": [
    "Medium"
  ],
  "maintenance": [
    "Medium"
  ],
  "light": [
    "Full sun (6 or more hours of direct sunlight a day)"
  ],
  "soil-drainage": [
    "Good Drainage"
  ],
  "available-space-to-plant": [
    "6-feet-12 feet",
    "12-24 feet"
  ],
  "usda-plant-hardiness-zone": [
    "5a",
    "5b",
    "6a",
    "6b",
    "7a",
    "7b",
    "8a",
    "8b"
  ],
  "fruit-color": [
    "Brown/Copper",
    "Gold/Yellow",
    "Red/Burgundy"
  ],
  "fruit-value-to-gardener": [
    "Edible"
  ],
  "display/harvest-time": [
    "Fall"
  ],
  "fruit-type": [
    "Pome"
  ],
  "fruit-width": [
    "1-3 inches"
  ],
  "fruit-description": [
    "Ovate to round 3\" in diameter green-yellow skin with some bronze to red blush at maturity and prominate lenticles.   Then turns deep yellow after storage.  Skin is non-waxy, flesh is medium to coarse grained, acidic, and bright but mellows after storage, resists growing with a complex spicy flavor.  Seeds are black-brown."
  ],
  "flower-color": [
    "Pink",
    "White"
  ],
  "flower-bloom-time": [
    "Spring"
  ],
  "flower-description": [
    "Rose to magenta fading to white margins appear in April"
  ],
  "leaf-color": [
    "Green"
  ],
  "leaf-type": [
    "Simple"
  ],
  "leaf-arrangement": [
    "Alternate"
  ],
  "leaf-shape": [
    "Ovate"
  ],
  "leaf-margin": [
    "Doubly Serrate",
    "Serrate"
  ],
  "hairs-present": [
    "No"
  ],
  "leaf-description": [
    "Simple, alternate, ovate to oval, serrate to double serrate margins, tips acute to acuminate, base acute to rounded.  Petioles have red pigmentation which is more prevalent with sun exposure."
  ],
  "stem-is-aromatic": "N",
  "landscape-theme": [
    "Children's Garden",
    "Edible Garden"
  ],
  "design-feature": [
    "Flowering Tree",
    "Small Tree"
  ],
  "resistance-to-challenges": [
    "Diseases",
    "Drought"
  ]
}