{
  "fullName": "Salix discolor",
  "name": "salix-discolor",
  "commonNames": [
    "Pussy Willow"
  ],
  "references": [
    {
      "url": "https://plants.ces.ncsu.edu/plants/salix-discolor/",
      "referenced": "general plant data"
    }
  ],
  "genus": "Salix",
  "species": "discolor",
  "family": "Salicaceae",
  "life-cycle": [
    "Woody"
  ],
  "recommended-propagation-strategy": [
    "Stem Cutting"
  ],
  "country-or-region-of-origin": [
    "North America"
  ],
  "wildlife-value": [
    "This plant supports Viceroy (Limenitis archippus) larvae which has two to three broods from May-September.  Adult butterflies feed on decaying matter, aphid honeydew, and nectar from composite flowers. Members of the Salix genus support the following specilized bees: Andrena (Parandrena) andrenoides, Andrena (Thysandrena) bisalicis, Andrena (Tylandrena) erythrogaster, Andrena (Andrena) frigida, Andrena (Micrandrena) illinoiensis, Andrena (Andrena) macoupinensis, Andrena (Trachandrena) mariae, Andrena (Parandrena) nida, Andrena (Micrandrena) nigrae, Andrena (Micrandrena) salictaria, Andrena (Parandrena) wellesleyana."
  ],
  "play-value": [
    "Attracts Pollinators",
    "Textural ",
    "Wildlife Food Source"
  ],
  "dimensions": [
    "Height: 10 ft. 0 in. - 20 ft. 0 in.",
    "Width: 8 ft. 0 in. - 12 ft. 0 in."
  ],
  "plant-type": [
    "Shrub"
  ],
  "woody-plant-leaf-characteristics": [
    "Deciduous",
    "Deciduous"
  ],
  "habit/form": [
    "Erect",
    "Multi-stemmed"
  ],
  "growth-rate": [
    "Rapid"
  ],
  "maintenance": [
    "Low"
  ],
  "texture": [
    "Medium"
  ],
  "light": [
    "Full sun (6 or more hours of direct sunlight a day)",
    "Partial Shade (Direct sunlight only part of the day, 2-6 hours)"
  ],
  "soil-drainage": [
    "Good Drainage",
    "Moist"
  ],
  "usda-plant-hardiness-zone": [
    "2a",
    "2b",
    "3a",
    "3b",
    "4a",
    "4b",
    "5a",
    "5b",
    "6a",
    "6b",
    "7a",
    "7b"
  ],
  "fruit-color": [
    "Brown/Copper"
  ],
  "display/harvest-time": [
    "Fall"
  ],
  "fruit-type": [
    "Capsule"
  ],
  "flower-color": [
    "Gray/Silver",
    "White"
  ],
  "flower-value-to-gardener": [
    "Good Cut",
    "Good Dried",
    "Long-lasting"
  ],
  "flower-bloom-time": [
    "Spring",
    "Winter"
  ],
  "flower-description": [
    "Silky gray male flowers in spring before leaves emerge on separate male and female plants"
  ],
  "leaf-color": [
    "Gray/Silver",
    "Green"
  ],
  "deciduous-leaf-fall-color": [
    "Gold/Yellow",
    "Insignificant"
  ],
  "leaf-type": [
    "Simple"
  ],
  "leaf-arrangement": [
    "Alternate"
  ],
  "hairs-present": [
    "No"
  ],
  "leaf-length": [
    "3-6 inches"
  ],
  "leaf-description": [
    "Alternate, simple leaves; 3 to 4 in. long; gray-green underside; non-showy fall color"
  ],
  "stem-is-aromatic": "N",
  "landscape-location": [
    "Lawn",
    "Meadow",
    "Pond",
    "Recreational Play Area"
  ],
  "landscape-theme": [
    "Butterfly Garden",
    "Children's Garden",
    "Pollinator Garden"
  ],
  "design-feature": [
    "Hedge"
  ],
  "attracts": [
    "Butterflies",
    "Pollinators",
    "Songbirds",
    "Specialized Bees"
  ],
  "resistance-to-challenges": [
    "Dry Soil"
  ],
  "uses": "Native Americans are known to have used this plant for medicinal purposes. It was also used in making rope, baskets, containers, fasteners, cooking tools, and in making netting."
}