{
  "fullName": "Sorghum bicolor",
  "name": "sorghum-bicolor",
  "commonNames": [
    "Common Wild Sorghum",
    "Durra",
    "Grain Sorghum",
    "Great Millet",
    "Indian Millet",
    "Jowar",
    "Milo",
    "Sorghum",
    "Sudangrass"
  ],
  "references": [
    {
      "url": "https://plants.ces.ncsu.edu/plants/sorghum-bicolor/",
      "referenced": "general plant data"
    }
  ],
  "genus": "Sorghum",
  "species": "bicolor",
  "family": "Poaceae",
  "life-cycle": [
    "Annual",
    "Perennial"
  ],
  "recommended-propagation-strategy": [
    "Seed"
  ],
  "country-or-region-of-origin": [
    "Africa"
  ],
  "distribution": [
    "Worldwide"
  ],
  "wildlife-value": [
    "Birds and small mamals are attracted to the seeds."
  ],
  "edibility": [
    "A grain that is used for human and livestock.  It can be cooked like rice.  It can also be ground into a flour. The grain from sorghum is gluten-free and is typically ground into a meal that is used for bread, porridge, and cakes.  Processing the grain will help to dissipate its strong taste.  It can also be used in the production of oils, starch, dextrose and even alcoholic drinks."
  ],
  "dimensions": [
    "Height: 2 ft. 0 in. - 3 ft. 0 in.",
    "Width: 2 ft. 0 in. - 3 ft. 0 in."
  ],
  "plant-type": [
    "Annual",
    "Edible",
    "Ornamental Grasses and Sedges",
    "Vegetable"
  ],
  "habit/form": [
    "Arching",
    "Columnar",
    "Erect"
  ],
  "growth-rate": [
    "Rapid"
  ],
  "maintenance": [
    "High"
  ],
  "texture": [
    "Medium"
  ],
  "light": [
    "Full sun (6 or more hours of direct sunlight a day)"
  ],
  "soil-texture": [
    "Clay",
    "Loam (Silt)",
    "Sand"
  ],
  "soil-ph": [
    "Acid (<6.0)",
    "Neutral (6.0-8.0)"
  ],
  "soil-drainage": [
    "Moist",
    "Occasionally Dry",
    "Very Dry"
  ],
  "available-space-to-plant": [
    "3 feet-6 feet"
  ],
  "usda-plant-hardiness-zone": [
    "2a",
    "2b",
    "3a",
    "3b",
    "4a",
    "4b",
    "5a",
    "5b",
    "6a",
    "6b",
    "7a",
    "7b",
    "8a",
    "8b",
    "9a",
    "9b",
    "10a",
    "10b",
    "11a",
    "11b"
  ],
  "fruit-color": [
    "Gold/Yellow"
  ],
  "fruit-value-to-gardener": [
    "Edible"
  ],
  "display/harvest-time": [
    "Fall"
  ],
  "fruit-length": [
    "< 1 inch"
  ],
  "fruit-width": [
    "< 1 inch"
  ],
  "fruit-description": [
    "Edible seeds ripen from September-October and vary in color from white through shades of red and brown to pale yellow to deep purple-brown."
  ],
  "flower-color": [
    "Brown/Copper",
    "Gold/Yellow"
  ],
  "flower-inflorescence": [
    "Insignificant",
    "Panicle"
  ],
  "flower-bloom-time": [
    "Fall",
    "Summer"
  ],
  "flower-size": [
    "< 1 inch"
  ],
  "flower-description": [
    "Wind pollinated flowers appear from August to October.  Growing in the form of 6\" to 20\" panicles, each flower cluster can produce 800 to 3,000 kernels."
  ],
  "leaf-color": [
    "Green"
  ],
  "leaf-feel": [
    "Waxy"
  ],
  "leaf-value-to-gardener": [
    "Edible"
  ],
  "leaf-type": [
    "Sheath",
    "Simple"
  ],
  "leaf-arrangement": [
    "Alternate"
  ],
  "leaf-shape": [
    "Lanceolate"
  ],
  "leaf-margin": [
    "Entire"
  ],
  "hairs-present": [
    "No"
  ],
  "leaf-length": [
    "> 6 inches"
  ],
  "leaf-width": [
    "1-3 inches"
  ],
  "leaf-description": [
    "Floppy leaf blades grow along the entire length of each stem.  They are located underneath the flower panicles.  The upper side of the leaf is a darker green than the underside.  The underside has a dull appearance."
  ],
  "stem-color": [
    "Green"
  ],
  "stem-is-aromatic": "N",
  "stem-surface": [
    "Smooth (glabrous)"
  ],
  "stem-description": [
    "Grows as a solitary or tufted leafy stem that is covered by sheaths."
  ],
  "landscape-location": [
    "Meadow"
  ],
  "attracts": [
    "Songbirds"
  ],
  "resistance-to-challenges": [
    "Drought",
    "Heat",
    "Poor Soil"
  ],
  "problems": [
    "Invasive Species",
    "Poisonous to Humans",
    "Problem for Horses",
    "Weedy"
  ],
  "poison-severity": [
    "Low"
  ],
  "poison-symptoms": [
    "Diarrhea, dizziness, drowsiness, tiredness, headache, loss of appetite, restlessness. Consumption of an immature plant is poisonous to both humans and animals.  This toxic nature can increase when the plant is exposed to frost, drought, or trampling.  If consumed in excess quantities, it can cause respiratory distress and death.  The poisonous substances found in immature plants are destroyed once the plant has dried or converted to food for animal consumption."
  ],
  "poison-toxic-principle": [
    "Hydrogen cyanide and hordenine."
  ],
  "causes-contact-dermatitis": [
    "No"
  ],
  "poison-part": [
    "Leaves",
    "Stems"
  ],
  "uses": "The grain can be used to make ethanol.  Used as cattle and poultry feed. Its stalks can be used as building material or to make brooms."
}