{
  "fullName": "Crataegus munda",
  "name": "crataegus-munda",
  "commonNames": [
    "Batesburg Hawthorn",
    "Dwarf Hawthorn",
    "Hawthorn",
    "Pexa Hawthorn"
  ],
  "references": [
    {
      "url": "https://plants.ces.ncsu.edu/plants/crataegus-munda/",
      "referenced": "general plant data"
    }
  ],
  "genus": "Crataegus",
  "species": "munda",
  "family": "Rosaceae",
  "life-cycle": [
    "Woody"
  ],
  "recommended-propagation-strategy": [
    "Seed"
  ],
  "country-or-region-of-origin": [
    "Southeastern United States"
  ],
  "distribution": [
    "Virginia south to Florida and west to Mississippi"
  ],
  "wildlife-value": [
    "Important nectar flower for insects; food plant of many moths including the eggar moth; haws provide winter fruit for songbirds. It is a larval host plant for Gray Hairstreak (Strymon melinus), Red-spotted Purple (Limenitis arthemis astyanax), and Viceroy (Limenitis archippus). Red-spotted Purple and Viceroy rarely use this host plant in North Carolina. Good nesting habitat with thorns providing protection from predators."
  ],
  "play-value": [
    "Attracts Pollinators",
    "Edible fruit ",
    "Wildlife Cover/Habitat",
    "Wildlife Food Source"
  ],
  "dimensions": [
    "Height: 3 ft. 0 in. - 5 ft. 0 in.",
    "Width: 2 ft. 0 in. - 4 ft. 0 in."
  ],
  "plant-type": [
    "Native Plant",
    "Shrub",
    "Tree"
  ],
  "woody-plant-leaf-characteristics": [
    "Deciduous",
    "Deciduous"
  ],
  "habit/form": [
    "Mounding",
    "Rounded"
  ],
  "growth-rate": [
    "Medium"
  ],
  "texture": [
    "Coarse"
  ],
  "appendage": [
    "Thorns"
  ],
  "light": [
    "Full sun (6 or more hours of direct sunlight a day)",
    "Partial Shade (Direct sunlight only part of the day, 2-6 hours)"
  ],
  "soil-texture": [
    "Clay",
    "Loam (Silt)",
    "Sand"
  ],
  "soil-drainage": [
    "Good Drainage"
  ],
  "usda-plant-hardiness-zone": [
    "7a",
    "7b",
    "8a",
    "8b",
    "9a",
    "9b"
  ],
  "fruit-color": [
    "Red/Burgundy"
  ],
  "fruit-value-to-gardener": [
    "Edible"
  ],
  "display/harvest-time": [
    "Fall"
  ],
  "fruit-type": [
    "Pome"
  ],
  "fruit-length": [
    "< 1 inch"
  ],
  "fruit-width": [
    "< 1 inch"
  ],
  "fruit-description": [
    "Small red pome with 1 to 5 pyrenes that resemble the “stones” in related plums, peaches, etc.  Sometimes called the ‘haw’. Matures Sept.- Oct."
  ],
  "flower-color": [
    "White"
  ],
  "flower-inflorescence": [
    "Corymb"
  ],
  "flower-bloom-time": [
    "Spring"
  ],
  "flower-shape": [
    "Cup"
  ],
  "flower-petals": [
    "4-5 petals/rays"
  ],
  "flower-size": [
    "< 1 inch"
  ],
  "flower-description": [
    "One or two flowers per inflorescence with 5-lobed calyx, 5 petals, usually 20 stamens (anthers usually white or yellow). Blooms March-May. Can have unpleasant odor that attracts midges for fertilization."
  ],
  "leaf-color": [
    "Green"
  ],
  "leaf-type": [
    "Simple"
  ],
  "leaf-arrangement": [
    "Alternate"
  ],
  "leaf-shape": [
    "Cuneate",
    "Ovate",
    "Spatulate"
  ],
  "leaf-margin": [
    "Crenate",
    "Lobed",
    "Serrate"
  ],
  "hairs-present": [
    "No"
  ],
  "leaf-length": [
    "1-3 inches"
  ],
  "leaf-width": [
    "< 1 inch"
  ],
  "leaf-description": [
    "One to one and a half inch long leaves are spatulate to cuneate,  with a base narrowly cuneate. Tips are rounded, lobes number 0 or 3 per side distally,  margins are serrulate-crenate on the distal 1/2 with glandular teeth."
  ],
  "bark-color": [
    "Dark Gray",
    "Light Gray"
  ],
  "surface/attachment": [
    "Smooth"
  ],
  "bark-description": [
    "Bark is thin, smooth, and gray. On old stems, it breaks up into narrow scales."
  ],
  "stem-color": [
    "Brown/Copper",
    "Green",
    "Purple/Lavender"
  ],
  "stem-is-aromatic": "N",
  "stem-form": [
    "Straight"
  ],
  "stem-surface": [
    "Smooth (glabrous)"
  ],
  "stem-description": [
    "New growth is green with suppressed hairs. Older stems are purple-brown, slender, straight and have numerous thorns. Stems sometimes winged for half its length."
  ],
  "landscape-location": [
    "Coastal",
    "Naturalized Area"
  ],
  "landscape-theme": [
    "Butterfly Garden",
    "Native Garden",
    "Pollinator Garden"
  ],
  "design-feature": [
    "Barrier"
  ],
  "attracts": [
    "Butterflies",
    "Pollinators",
    "Small Mammals",
    "Songbirds"
  ],
  "uses": "The leaves, berries, and flowers are used in medicines and herbals for cardiovascular health. The wood is strong, tough, and hard, but has little commercial value."
}