{
  "fullName": "Peperomia rotundifolia",
  "name": "peperomia-rotundifolia",
  "commonNames": [
    "Creeping Buttons",
    "Jade Necklace",
    "Peperomia Rotundifolia",
    "Round Leaf Peperomia",
    "Trailing Jade",
    "Yorba Linda"
  ],
  "references": [
    {
      "url": "https://plants.ces.ncsu.edu/plants/peperomia-rotundifolia/",
      "referenced": "general plant data"
    }
  ],
  "genus": "Peperomia",
  "species": "rotundifolia",
  "family": "Piperaceae",
  "life-cycle": [
    "Perennial"
  ],
  "recommended-propagation-strategy": [
    "Stem Cutting"
  ],
  "country-or-region-of-origin": [
    "Mexico to Tropical America"
  ],
  "distribution": [
    "Argentina",
    "Belize",
    "Bolivia",
    "Brazil",
    "Colombia",
    "Costa Rica",
    "Cuba",
    "Dominican Republic",
    "Ecuador",
    "Guatemala",
    "Haiti",
    "Honduras",
    "Jamaica",
    "Mexico",
    "Nicaragua",
    "Panama",
    "Paraguay",
    "Puerto Rico",
    "Suriname",
    "Trinidad-Tobago",
    "and Venezuela"
  ],
  "play-value": [
    "Easy to Grow"
  ],
  "plant-type": [
    "Epiphyte",
    "Herbaceous Perennial",
    "Houseplant"
  ],
  "habit/form": [
    "Creeping"
  ],
  "growth-rate": [
    "Slow"
  ],
  "maintenance": [
    "Low"
  ],
  "texture": [
    "Medium"
  ],
  "light": [
    "Dappled Sunlight (Shade through upper canopy all day)",
    "Partial Shade (Direct sunlight only part of the day, 2-6 hours)"
  ],
  "soil-texture": [
    "Loam (Silt)",
    "Sand"
  ],
  "soil-ph": [
    "Acid (<6.0)"
  ],
  "soil-drainage": [
    "Good Drainage",
    "Moist"
  ],
  "available-space-to-plant": [
    "12 inches-3 feet"
  ],
  "usda-plant-hardiness-zone": [
    "10a",
    "10b",
    "11a",
    "11b",
    "12a",
    "12b"
  ],
  "flower-color": [
    "Gold/Yellow"
  ],
  "flower-inflorescence": [
    "Spike"
  ],
  "flower-description": [
    "The flowers are short yellowish spikes. Indoor plants rarely flower."
  ],
  "leaf-color": [
    "Green"
  ],
  "leaf-feel": [
    "Fleshy"
  ],
  "leaf-value-to-gardener": [
    "Showy"
  ],
  "leaf-type": [
    "Simple"
  ],
  "leaf-shape": [
    "Orbicular"
  ],
  "hairs-present": [
    "No"
  ],
  "leaf-length": [
    "< 1 inch"
  ],
  "leaf-width": [
    "< 1 inch"
  ],
  "leaf-description": [
    "Bright green, thick rounded leaves, and less than 0.5 inches in diameter."
  ],
  "stem-color": [
    "Brown/Copper"
  ],
  "stem-is-aromatic": "N",
  "stem-surface": [
    "Hairy (pubescent)"
  ],
  "stem-description": [
    "Slender, fleshy, brownish stems with tiny fine hairs."
  ],
  "landscape-location": [
    "Hanging Baskets",
    "Houseplants"
  ],
  "design-feature": [
    "Accent"
  ]
}