{
  "fullName": "Pinus rigida",
  "name": "pinus-rigida",
  "commonNames": [
    "Black Pine",
    "Hard Pine",
    "Northern Pitch Pine",
    "Pitch Pine",
    "Torch Pine",
    "Yellow Pine"
  ],
  "references": [
    {
      "url": "https://plants.ces.ncsu.edu/plants/pinus-rigida/",
      "referenced": "general plant data"
    }
  ],
  "genus": "Pinus",
  "species": "rigida",
  "family": "Pinaceae",
  "life-cycle": [
    "Woody"
  ],
  "recommended-propagation-strategy": [
    "Seed"
  ],
  "country-or-region-of-origin": [
    "Canada, portions of northeast US"
  ],
  "distribution": [
    "Canada west to Minnesota south to Georgia east up to Maine"
  ],
  "fire-risk-rating": [
    "medium flammability"
  ],
  "wildlife-value": [
    "This plant supports Imperial Moth (Eacles imperialis) larvae which have one brood per season and appear from April-October in the south. Adult Imperial Moths do not feed. In the Appalachia Mountains, wild boar eat the bark and soft outside wood of the roots."
  ],
  "particularly-resistant-to-insects/diseases/other-problems": [
    "Heat and drought tolerant."
  ],
  "dimensions": [
    "Height: 40 ft. 0 in. - 60 ft. 0 in.",
    "Width: 30 ft. 0 in. - 50 ft. 0 in."
  ],
  "plant-type": [
    "Native Plant",
    "Tree"
  ],
  "woody-plant-leaf-characteristics": [
    "Needled Evergreen",
    "Needled Evergreen"
  ],
  "habit/form": [
    "Open",
    "Pyramidal"
  ],
  "growth-rate": [
    "Medium"
  ],
  "texture": [
    "Medium"
  ],
  "light": [
    "Full sun (6 or more hours of direct sunlight a day)",
    "Partial Shade (Direct sunlight only part of the day, 2-6 hours)"
  ],
  "soil-texture": [
    "Sand"
  ],
  "soil-ph": [
    "Acid (<6.0)"
  ],
  "soil-drainage": [
    "Good Drainage",
    "Moist",
    "Occasionally Dry"
  ],
  "available-space-to-plant": [
    "24-60 feet"
  ],
  "usda-plant-hardiness-zone": [
    "4a",
    "4b",
    "5a",
    "5b",
    "6a",
    "6b",
    "7a",
    "7b"
  ],
  "fruit-color": [
    "Brown/Copper"
  ],
  "display/harvest-time": [
    "Fall"
  ],
  "fruit-description": [
    "Approximately 1 to 3 in. light brown cones in whorls of 3 to 5.  The spines on each scale are stiff and curved.  After releasing seeds, the cones will stay attached to the three for several years. Fruit displays from September to October."
  ],
  "flower-bloom-time": [
    "Spring"
  ],
  "flower-size": [
    "3-6 inches"
  ],
  "flower-description": [
    "Flowers bloom in May."
  ],
  "leaf-color": [
    "Gold/Yellow",
    "Green"
  ],
  "leaf-type": [
    "Needles",
    "Simple"
  ],
  "leaf-arrangement": [
    "Other/more complex"
  ],
  "leaf-shape": [
    "Acicular"
  ],
  "leaf-margin": [
    "Serrate"
  ],
  "hairs-present": [
    "No"
  ],
  "leaf-length": [
    "3-6 inches"
  ],
  "leaf-width": [
    "3-6 inches"
  ],
  "leaf-description": [
    "3 to 5 in. rigid, twisted dark yellow-green needles in bundles of 3 (3 per fascicle).  Three faces of each needle have many thin, white lines of stomata."
  ],
  "bark-color": [
    "Light Brown",
    "Red/Burgundy"
  ],
  "surface/attachment": [
    "Furrowed",
    "Ridges",
    "Shredding"
  ],
  "bark-plate-shape": [
    "Irregular"
  ],
  "bark-description": [
    "Thick, yellowish-brown plates.  Tufts of needles can be found growing on the trunk. Dark scaly young bark, red-brown or yellow-brown thick flat plated deep furrowed mature bark"
  ],
  "stem-color": [
    "Brown/Copper"
  ],
  "stem-is-aromatic": "N",
  "stem-description": [
    "Thick, gnarled, and sometimes pendulous."
  ],
  "landscape-location": [
    "Slope/Bank",
    "Woodland"
  ],
  "landscape-theme": [
    "Native Garden",
    "Nighttime Garden",
    "Winter Garden"
  ],
  "attracts": [
    "Moths",
    "Small Mammals",
    "Songbirds"
  ],
  "resistance-to-challenges": [
    "Deer",
    "Dry Soil",
    "Poor Soil",
    "Salt"
  ],
  "uses": "Lumber and wood pulp. Native Americans used to use pitch as a laxative and turpentine."
}