{
  "fullName": "Scheuchzeria palustris",
  "name": "scheuchzeria-palustris",
  "commonNames": [
    "Pod Grass",
    "Rannoch-rush",
    "Scheuchzeria"
  ],
  "references": [
    {
      "url": "https://plants.ces.ncsu.edu/plants/scheuchzeria-palustris/",
      "referenced": "general plant data"
    }
  ],
  "genus": "Scheuchzeria",
  "species": "palustris",
  "family": "Scheuchzeriaceae",
  "life-cycle": [
    "Perennial"
  ],
  "country-or-region-of-origin": [
    "Temperate northern hemisphere"
  ],
  "plant-type": [
    "Ornamental Grasses and Sedges",
    "Perennial"
  ],
  "habit/form": [
    "Arching",
    "Ascending"
  ],
  "available-space-to-plant": [
    "Less than 12 inches"
  ],
  "fruit-color": [
    "Gold/Yellow",
    "Green"
  ],
  "fruit-type": [
    "Capsule"
  ],
  "fruit-length": [
    "< 1 inch"
  ],
  "fruit-description": [
    "Three parted capsules with two seeds each green maturing to yellow 1/4\" long.   Seeds are elliptic, and dark brown 4 mm long."
  ],
  "flower-color": [
    "Cream/Tan",
    "Purple/Lavender",
    "White"
  ],
  "flower-inflorescence": [
    "Raceme"
  ],
  "flower-petals": [
    "6 petals/rays",
    "Tepals"
  ],
  "flower-size": [
    "< 1 inch"
  ],
  "flower-description": [
    "1/4\" wide 3 to 6 stalked flowers with six tepals each on a raceme alternately arranged on a stem.   Flowers are purple brown to creamy white in color."
  ],
  "leaf-color": [
    "Green"
  ],
  "leaf-type": [
    "Simple"
  ],
  "leaf-shape": [
    "Linear"
  ],
  "leaf-margin": [
    "Entire"
  ],
  "hairs-present": [
    "No"
  ],
  "leaf-length": [
    "> 6 inches"
  ],
  "leaf-width": [
    "< 1 inch"
  ],
  "leaf-description": [
    "Grass-like leaves smooth margins, no hairs, stalkless and an open hole at the end.  Lower leaves can reach a length of 16\" and width of 1/8\" but get smaller as they ascend the stems. Leaf bases sheath the stem and have a membrane where it meets the blade"
  ],
  "stem-is-aromatic": "N"
}