{
  "fullName": "Sorghastrum nutans",
  "name": "sorghastrum-nutans",
  "commonNames": [
    "Indiangrass",
    "Yellow Indiangrass"
  ],
  "references": [
    {
      "url": "https://plants.ces.ncsu.edu/plants/sorghastrum-nutans/",
      "referenced": "general plant data"
    }
  ],
  "genus": "Sorghastrum",
  "species": "nutans",
  "family": "Poaceae",
  "life-cycle": [
    "Perennial"
  ],
  "recommended-propagation-strategy": [
    "Seed"
  ],
  "country-or-region-of-origin": [
    "Native to Southeastern United States and Central America"
  ],
  "fire-risk-rating": [
    "extreme flammability"
  ],
  "wildlife-value": [
    "Provides excellent cover year-round. Seeds are eaten by songbirds and small mammals. Preferred food source for various grasshopper species."
  ],
  "particularly-resistant-to-insects/diseases/other-problems": [
    "Can withstand drought-like conditions."
  ],
  "dimensions": [
    "Height: 5 ft. 0 in. - 7 ft. 0 in.",
    "Width: 1 ft. 0 in. - 2 ft. 0 in."
  ],
  "plant-type": [
    "Native Plant",
    "Ornamental Grasses and Sedges",
    "Perennial"
  ],
  "woody-plant-leaf-characteristics": [
    "Deciduous",
    "Deciduous"
  ],
  "habit/form": [
    "Clumping",
    "Erect"
  ],
  "maintenance": [
    "Medium"
  ],
  "light": [
    "Full sun (6 or more hours of direct sunlight a day)"
  ],
  "soil-texture": [
    "Clay",
    "Shallow Rocky"
  ],
  "soil-drainage": [
    "Good Drainage",
    "Moist",
    "Occasionally Dry"
  ],
  "usda-plant-hardiness-zone": [
    "4a",
    "4b",
    "5a",
    "5b",
    "6a",
    "6b",
    "7a",
    "7b",
    "8a",
    "8b",
    "9a",
    "9b"
  ],
  "display/harvest-time": [
    "Fall"
  ],
  "fruit-type": [
    "Caryopsis"
  ],
  "fruit-description": [
    "Caryopsis 2 mm long. Displays from September to November."
  ],
  "flower-color": [
    "Gold/Yellow",
    "Orange"
  ],
  "flower-inflorescence": [
    "Panicle"
  ],
  "flower-value-to-gardener": [
    "Good Dried",
    "Long Bloom Season"
  ],
  "flower-bloom-time": [
    "Fall"
  ],
  "flower-size": [
    "> 6 inches"
  ],
  "flower-description": [
    "Flower panicles with a triad of spikelets extend above the foliage from August to October. Stiff, vertical flowering stems, topped with narrow, feathery, light brown flower panicles (to 12\" long) highlighted with yellow stamens, rise well above the foliage clump in late summer to 5-6' tall. Panicles darken to bronze/chestnut brown in fall as they mature, later fading to gray. Panicles continue to provide some interest well into winter."
  ],
  "leaf-color": [
    "Green",
    "Orange",
    "Purple/Lavender"
  ],
  "leaf-value-to-gardener": [
    "Long-lasting",
    "Showy"
  ],
  "deciduous-leaf-fall-color": [
    "Gold/Yellow",
    "Orange"
  ],
  "leaf-type": [
    "Sheath"
  ],
  "leaf-arrangement": [
    "Alternate"
  ],
  "hairs-present": [
    "No"
  ],
  "leaf-length": [
    "1-3 inches"
  ],
  "leaf-width": [
    "< 1 inch"
  ],
  "leaf-description": [
    "Forms upright clumps of slender, blue-green leaves (to 1/2\" wide and 2' long). Foliage turns orange-yellow in fall and usually retains hints of color into the winter. Sheathing leaves with attenuate apex and glabrous or pubescent surface."
  ],
  "stem-is-aromatic": "N",
  "landscape-location": [
    "Naturalized Area",
    "Pond"
  ],
  "landscape-theme": [
    "Butterfly Garden",
    "Native Garden",
    "Rain Garden"
  ],
  "design-feature": [
    "Mass Planting"
  ],
  "attracts": [
    "Butterflies",
    "Small Mammals",
    "Songbirds"
  ],
  "resistance-to-challenges": [
    "Black Walnut",
    "Deer",
    "Drought",
    "Dry Soil",
    "Erosion",
    "Wet Soil"
  ]
}