{
  "fullName": "Tagetes patula",
  "name": "tagetes-patula",
  "commonNames": [
    "French Marigold"
  ],
  "references": [
    {
      "url": "https://plants.ces.ncsu.edu/plants/tagetes-patula/",
      "referenced": "general plant data"
    }
  ],
  "genus": "Tagetes",
  "species": "patula",
  "family": "Asteraceae",
  "life-cycle": [
    "Annual"
  ],
  "country-or-region-of-origin": [
    "Mexico, Guatamala"
  ],
  "wildlife-value": [
    "Deer Resistant"
  ],
  "particularly-resistant-to-insects/diseases/other-problems": [
    "Some cultivars have shown good resistance to abiotic disorder."
  ],
  "edibility": [
    "Flowers are used to make refreshing drinks and the leaves are used for flavoring."
  ],
  "dimensions": [
    "Height: 0 ft. 6 in. - 1 ft. 0 in.",
    "Width: 0 ft. 6 in. - 1 ft. 6 in."
  ],
  "plant-type": [
    "Annual",
    "Poisonous"
  ],
  "habit/form": [
    "Clumping"
  ],
  "growth-rate": [
    "Medium"
  ],
  "maintenance": [
    "Low"
  ],
  "texture": [
    "Fine"
  ],
  "light": [
    "Full sun (6 or more hours of direct sunlight a day)",
    "Partial Shade (Direct sunlight only part of the day, 2-6 hours)"
  ],
  "soil-texture": [
    "Clay",
    "Loam (Silt)",
    "Sand"
  ],
  "soil-ph": [
    "Acid (<6.0)",
    "Neutral (6.0-8.0)"
  ],
  "soil-drainage": [
    "Good Drainage",
    "Occasionally Dry"
  ],
  "available-space-to-plant": [
    "Less than 12 inches"
  ],
  "flower-color": [
    "Brown/Copper",
    "Gold/Yellow",
    "Orange",
    "Red/Burgundy",
    "Variegated"
  ],
  "flower-inflorescence": [
    "Head"
  ],
  "flower-value-to-gardener": [
    "Edible",
    "Fragrant",
    "Long Bloom Season",
    "Showy"
  ],
  "flower-bloom-time": [
    "Fall",
    "Spring",
    "Summer"
  ],
  "flower-shape": [
    "Radial",
    "Saucer"
  ],
  "flower-size": [
    "1-3 inches"
  ],
  "flower-description": [
    "1-2 inch wide flower heads are single, semi or fully double, or crested blooms that come in various color combinations of yellows, reds, and oranges."
  ],
  "leaf-color": [
    "Green"
  ],
  "leaf-value-to-gardener": [
    "Fragrant"
  ],
  "leaf-type": [
    "Compound (Pinnately , Bipinnately, Palmately)"
  ],
  "leaf-arrangement": [
    "Alternate",
    "Opposite"
  ],
  "leaf-shape": [
    "Lanceolate"
  ],
  "leaf-margin": [
    "Dentate"
  ],
  "hairs-present": [
    "No"
  ],
  "leaf-length": [
    "1-3 inches"
  ],
  "leaf-width": [
    "< 1 inch"
  ],
  "leaf-description": [
    "Pinnately compound leaves are up to 6 inches long and have varying numbers of lance-shaped leaflets that are 2 or fewer inches long."
  ],
  "stem-is-aromatic": "N",
  "landscape-location": [
    "Container",
    "Houseplants",
    "Patio",
    "Pool/Hardscape",
    "Recreational Play Area"
  ],
  "landscape-theme": [
    "Butterfly Garden",
    "Children's Garden",
    "Cutting Garden",
    "Drought Tolerant Garden",
    "Edible Garden",
    "Garden for the Blind"
  ],
  "design-feature": [
    "Accent",
    "Border",
    "Mass Planting",
    "Small groups"
  ],
  "attracts": [
    "Butterflies"
  ],
  "resistance-to-challenges": [
    "Deer"
  ],
  "problems": [
    "Allelopathic",
    "Contact Dermatitis"
  ],
  "poison-severity": [
    "Low"
  ],
  "poison-symptoms": [
    "Skin redness, burning pain, and blisters when broken skin is in contact with cell sap plus sunlight; nose and eye irritation from aroma of flowers."
  ],
  "poison-toxic-principle": [
    "Phototoxic thiophene derivatives"
  ],
  "causes-contact-dermatitis": [
    "Yes"
  ],
  "poison-part": [
    "Flowers",
    "Leaves",
    "Roots"
  ],
  "uses": "The plant is used in herbal medicine. The scent of foliage deters insects, roots exude a chemical that repels soil nematodes. The flowers can be used as a yellow dye."
}